{
	"info": {
		"_postman_id": "58e670b3-0c62-45a4-87e6-c487fbb46bdf",
		"name": "Pruebas Peticiones Baz",
		"schema": "https://schema.getpostman.com/json/collection/v2.1.0/collection.json",
		"_exporter_id": "12033345"
	},
	"item": [
		{
			"name": "Crear Usuario",
			"request": {
				"method": "POST",
				"header": [],
				"url": {
					"raw": "https://localhost:8102/user/create",
					"protocol": "https",
					"host": [
						"localhost"
					],
					"port": "8102",
					"path": [
						"user",
						"create"
					]
				}
			},
			"response": []
		},
		{
			"name": "Obtener Usuarios",
			"request": {
				"method": "GET",
				"header": [],
				"url": {
					"raw": "http://localhost:8080/user/getUsers",
					"protocol": "http",
					"host": [
						"localhost"
					],
					"port": "8080",
					"path": [
						"user",
						"getUsers"
					]
				}
			},
			"response": []
		},
		{
			"name": "Obtener Usuario por ID",
			"request": {
				"method": "PUT",
				"header": [],
				"url": {
					"raw": "http://localhost:8080/user/update",
					"protocol": "http",
					"host": [
						"localhost"
					],
					"port": "8080",
					"path": [
						"user",
						"update"
					]
				}
			},
			"response": []
		},
		{
			"name": "Eliminar Usuario",
			"request": {
				"method": "DELETE",
				"header": [],
				"body": {
					"mode": "raw",
					"raw": "{\r\n \"userId\": \"6341cb13abcf791a0f69e2eb\",\r\n  \"name\" : \"Jim\",\r\n  \"userSettings\" : {\r\n    \"bike\" : \"pulsar\"\r\n  }\r\n}",
					"options": {
						"raw": {
							"language": "json"
						}
					}
				},
				"url": {
					"raw": "http://localhost:8080/user/delete",
					"protocol": "http",
					"host": [
						"localhost"
					],
					"port": "8080",
					"path": [
						"user",
						"delete"
					]
				}
			},
			"response": []
		},
		{
			"name": "Consumir Api Publica",
			"request": {
				"method": "GET",
				"header": [],
				"url": {
					"raw": "http://localhost:8080/buscarComentarios",
					"protocol": "http",
					"host": [
						"localhost"
					],
					"port": "8080",
					"path": [
						"buscarComentarios"
					]
				}
			},
			"response": []
		}
	]
}